app.py
auth.py
codicent_cli-0.5.0.dist-info/licenses/LICENSE
codicent_cli-0.5.0.dist-info/METADATA
codicent_cli-0.5.0.dist-info/WHEEL
codicent_cli-0.5.0.dist-info/entry_points.txt
codicent_cli-0.5.0.dist-info/top_level.txt
codicent_cli-0.5.0.dist-info/RECORD
