Metadata-Version: 2.4
Name: codicent-cli
Version: 0.5.0
Summary: Command-line interface for the Codicent API
Home-page: https://github.com/izaxon/codicent-cli
Author: Johan Isaksson
Author-email: johan@izaxon.com
Project-URL: Bug Reports, https://github.com/izaxon/codicent-cli/issues
Project-URL: Source, https://github.com/izaxon/codicent-cli
Keywords: codicent cli api chat ai
Classifier: Development Status :: 4 - Beta
Classifier: Intended Audience :: Developers
Classifier: Topic :: Software Development :: Libraries :: Python Modules
Classifier: License :: OSI Approved :: MIT License
Classifier: Programming Language :: Python :: 3
Classifier: Programming Language :: Python :: 3.6
Classifier: Programming Language :: Python :: 3.7
Classifier: Programming Language :: Python :: 3.8
Classifier: Programming Language :: Python :: 3.9
Classifier: Programming Language :: Python :: 3.10
Classifier: Programming Language :: Python :: 3.11
Classifier: Programming Language :: Python :: 3.12
Requires-Python: >=3.6
License-File: LICENSE
Requires-Dist: rich
Requires-Dist: codicent-py
Requires-Dist: prompt_toolkit
Requires-Dist: requests
Dynamic: author
Dynamic: author-email
Dynamic: classifier
Dynamic: description
Dynamic: description-content-type
Dynamic: home-page
Dynamic: keywords
Dynamic: license-file
Dynamic: project-url
Dynamic: requires-dist
Dynamic: requires-python
Dynamic: summary
